[
  {
    "type": "cc.Sprite",
    "value": {
      "_name": {
        "type": "String",
        "value": ""
      },
      "_objFlags": {
        "type": "Float",
        "value": 63488
      },
      "node": {
        "value": {
          "name": "bj_zjm_jb",
          "uuid": "2cKipBr4hNPYVL5JJ1t3zT"
        },
        "type": "cc.Node"
      },
      "name": {
        "type": "String",
        "value": "bj_zjm_jb<Sprite>"
      },
      "uuid": {
        "type": "String",
        "value": "7dyXCzylBJnJrLVzrLLxw2"
      },
      "__scriptAsset": {
        "type": "cc.Script",
        "value": {
          "uuid": ""
        }
      },
      "_enabled": {
        "type": "Boolean",
        "value": true
      },
      "enabled": {
        "type": "Boolean",
        "value": true
      },
      "enabledInHierarchy": {
        "type": "Boolean",
        "value": true
      },
      "_isOnLoadCalled": {
        "type": "Float",
        "value": 16384
      },
      "_materials": {
        "type": "cc.Material",
        "value": [
          {
            "type": "cc.MaterialVariant",
            "value": {
              "uuid": "eca5d2f2-8ef6-41c2-bbe6-f9c79d09c432"
            }
          }
        ]
      },
      "materials": {
        "type": "cc.Material",
        "value": [
          {
            "type": "cc.MaterialVariant",
            "value": {
              "uuid": "eca5d2f2-8ef6-41c2-bbe6-f9c79d09c432"
            }
          }
        ]
      },
      "_srcBlendFactor": {
        "type": "Float",
        "value": 770
      },
      "_dstBlendFactor": {
        "type": "Float",
        "value": 771
      },
      "srcBlendFactor": {
        "type": "Enum",
        "value": 770
      },
      "dstBlendFactor": {
        "type": "Enum",
        "value": 771
      },
      "_spriteFrame": {
        "type": "cc.SpriteFrame",
        "value": {
          "uuid": "65ca6eca-d60b-4fc8-bd21-5489db0f6a9e"
        }
      },
      "_type": {
        "type": "Float",
        "value": 0
      },
      "_sizeMode": {
        "type": "Float",
        "value": 0
      },
      "_fillType": {
        "type": "Float",
        "value": 0
      },
      "_fillCenter": {
        "type": "cc.Vec2",
        "value": {
          "x": 0,
          "y": 0
        }
      },
      "_fillStart": {
        "type": "Float",
        "value": 0
      },
      "_fillRange": {
        "type": "Float",
        "value": 0
      },
      "_isTrimmedMode": {
        "type": "Boolean",
        "value": true
      },
      "_atlas": {
        "type": "cc.SpriteAtlas",
        "value": {
          "uuid": ""
        }
      },
      "spriteFrame": {
        "type": "cc.SpriteFrame",
        "value": {
          "uuid": "65ca6eca-d60b-4fc8-bd21-5489db0f6a9e"
        }
      },
      "type": {
        "type": "Enum",
        "value": 0
      },
      "fillType": {
        "type": "Enum",
        "value": 0
      },
      "fillCenter": {
        "type": "cc.Vec2",
        "value": {
          "x": 0,
          "y": 0
        }
      },
      "fillStart": {
        "type": "Float",
        "value": 0
      },
      "fillRange": {
        "type": "Float",
        "value": 0
      },
      "trim": {
        "type": "Boolean",
        "value": true
      },
      "sizeMode": {
        "type": "Enum",
        "value": 0
      },
      "_id": {
        "type": "string",
        "value": "7dyXCzylBJnJrLVzrLLxw2"
      }
    }
  },
  {
    "type": "cc.Widget",
    "value": {
      "_name": {
        "type": "String",
        "value": ""
      },
      "_objFlags": {
        "type": "Float",
        "value": 63488
      },
      "node": {
        "value": {
          "name": "bj_zjm_jb",
          "uuid": "2cKipBr4hNPYVL5JJ1t3zT"
        },
        "type": "cc.Node"
      },
      "name": {
        "type": "String",
        "value": "bj_zjm_jb<Widget>"
      },
      "uuid": {
        "type": "String",
        "value": "2fipzI9JpOOoRksfmsTPmE"
      },
      "__scriptAsset": {
        "type": "cc.Script",
        "value": {
          "uuid": ""
        }
      },
      "_enabled": {
        "type": "Boolean",
        "value": true
      },
      "enabled": {
        "type": "Boolean",
        "value": true
      },
      "enabledInHierarchy": {
        "type": "Boolean",
        "value": true
      },
      "_isOnLoadCalled": {
        "type": "Float",
        "value": 16384
      },
      "target": {
        "type": "cc.Node",
        "value": {
          "uuid": ""
        }
      },
      "isAlignTop": {
        "type": "Boolean",
        "value": false
      },
      "isAlignVerticalCenter": {
        "type": "Boolean",
        "value": false
      },
      "isAlignBottom": {
        "type": "Boolean",
        "value": false
      },
      "isAlignLeft": {
        "type": "Boolean",
        "value": true
      },
      "isAlignHorizontalCenter": {
        "type": "Boolean",
        "value": false
      },
      "isAlignRight": {
        "type": "Boolean",
        "value": true
      },
      "isStretchWidth": {
        "type": "Boolean",
        "value": true
      },
      "isStretchHeight": {
        "type": "Boolean",
        "value": false
      },
      "top": {
        "type": "Float",
        "value": 0
      },
      "bottom": {
        "type": "Float",
        "value": 0
      },
      "left": {
        "type": "Float",
        "value": 0
      },
      "right": {
        "type": "Float",
        "value": 0
      },
      "horizontalCenter": {
        "type": "Float",
        "value": 0
      },
      "verticalCenter": {
        "type": "Float",
        "value": 0
      },
      "isAbsoluteHorizontalCenter": {
        "type": "Boolean",
        "value": true
      },
      "isAbsoluteVerticalCenter": {
        "type": "Boolean",
        "value": true
      },
      "isAbsoluteTop": {
        "type": "Boolean",
        "value": true
      },
      "isAbsoluteBottom": {
        "type": "Boolean",
        "value": true
      },
      "isAbsoluteLeft": {
        "type": "Boolean",
        "value": true
      },
      "isAbsoluteRight": {
        "type": "Boolean",
        "value": true
      },
      "alignMode": {
        "type": "Enum",
        "value": 1
      },
      "_wasAlignOnce": {
        "type": "Object",
        "value": null
      },
      "_target": {
        "type": "Object",
        "value": null
      },
      "_alignFlags": {
        "type": "Float",
        "value": 40
      },
      "_left": {
        "type": "Float",
        "value": 0
      },
      "_right": {
        "type": "Float",
        "value": 0
      },
      "_top": {
        "type": "Float",
        "value": 0
      },
      "_bottom": {
        "type": "Float",
        "value": 0
      },
      "_verticalCenter": {
        "type": "Float",
        "value": 0
      },
      "_horizontalCenter": {
        "type": "Float",
        "value": 0
      },
      "_isAbsLeft": {
        "type": "Boolean",
        "value": true
      },
      "_isAbsRight": {
        "type": "Boolean",
        "value": true
      },
      "_isAbsTop": {
        "type": "Boolean",
        "value": true
      },
      "_isAbsBottom": {
        "type": "Boolean",
        "value": true
      },
      "_isAbsHorizontalCenter": {
        "type": "Boolean",
        "value": true
      },
      "_isAbsVerticalCenter": {
        "type": "Boolean",
        "value": true
      },
      "_originalWidth": {
        "type": "Float",
        "value": 750
      },
      "_originalHeight": {
        "type": "Float",
        "value": 1334
      },
      "_id": {
        "type": "string",
        "value": "2fipzI9JpOOoRksfmsTPmE"
      }
    }
  }
]